<?xml version="1.0" encoding="utf-8" ?>
<manifest>
  <control namespace="MegaPCF" constructor="DebugPanel" version="1.0.0" display-name-key="DebugPanel" description-key="Developer debug info panel" control-type="standard">
    <external-service-usage enabled="false">
    </external-service-usage>

    <property name="sampleProperty" display-name-key="Sample Property" description-key="A sample input property for DebugPanel." of-type="SingleLine.Text" usage="bound" required="true" />

    <resources>
      <code path="index.ts" order="1" />
    </resources>

    <feature-usage>
      <uses-feature name="WebAPI" required="false" />
    </feature-usage>
  </control>
</manifest>
